crystal_builder_step/__init__.py
crystal_builder_step/_version.py
crystal_builder_step/crystal_builder.py
crystal_builder_step/crystal_builder_parameters.py
crystal_builder_step/crystal_builder_step.py
crystal_builder_step/crystal_metadata.py
crystal_builder_step/parse.py
crystal_builder_step/tk_crystal_builder.py
crystal_builder_step/data/A10B2C_hP39_171_5c_c_a.cif
crystal_builder_step/data/A10B2C_hP39_172_5c_c_a.cif
crystal_builder_step/data/A10B3C4_oC68_64_2dfg_ad_2d.cif
crystal_builder_step/data/A10B3C4_oP68_55_2e2fgh2i_adef_2e2f.cif
crystal_builder_step/data/A10B3_oF52_42_2abce_ab.cif
crystal_builder_step/data/A10B4C3_tI34_139_c2eg_2e_ae.cif
crystal_builder_step/data/A10B7_hP34_176_c3h_b2h.cif
crystal_builder_step/data/A10B_cF44_225_cf_b.cif
crystal_builder_step/data/A10B_hP22_194_bhj_c.cif
crystal_builder_step/data/A11B2C2_mP60_4_22a_4a_4a.cif
crystal_builder_step/data/A11B3_mP56_14_11e_3e.cif
crystal_builder_step/data/A11B4_cF120_227_acdf_e.cif
crystal_builder_step/data/A12B19C_hP64_194_ab2fk_efh2k_d.cif
crystal_builder_step/data/A12B2CD12_aP54_2_12i_2i_i_12i.cif
crystal_builder_step/data/A12B2C_cF60_196_h_bc_a.cif
crystal_builder_step/data/A12B36CD12_cF488_210_h_3h_a_fg.cif
crystal_builder_step/data/A12B6C_cF608_210_4h_2h_e.cif
crystal_builder_step/data/A12B7C2_hP21_174_2j2k_ajk_cf.cif
crystal_builder_step/data/A12BC10D_tP96_92_6b_a_5b_a.cif
crystal_builder_step/data/A12BC4_cP34_195_2j_ab_2e.cif
crystal_builder_step/data/A12B_cF52_225_i_a.cif
crystal_builder_step/data/A12B_cI26_204_g_a.cif
crystal_builder_step/data/A12B_hP13_191_cdei_a.cif
crystal_builder_step/data/A12B_tI26_139_fij_a.cif
crystal_builder_step/data/A13B2C2_oP34_32_a6c_c_c.cif
crystal_builder_step/data/A13B2_hR15_166_b2h_c.cif
crystal_builder_step/data/A13B4_mC102_12_dg8i5j_4ij.cif
crystal_builder_step/data/A13B4_mC102_8_17a11b_8a2b.cif
crystal_builder_step/data/A13B4_mC34_12_b6i_2i.cif
crystal_builder_step/data/A13B4_oP102_31_17a11b_8a2b.cif
crystal_builder_step-2022.7.31.dist-info/AUTHORS.rst
crystal_builder_step-2022.7.31.dist-info/LICENSE
crystal_builder_step-2022.7.31.dist-info/METADATA
crystal_builder_step-2022.7.31.dist-info/WHEEL
crystal_builder_step-2022.7.31.dist-info/entry_points.txt
crystal_builder_step-2022.7.31.dist-info/top_level.txt
crystal_builder_step-2022.7.31.dist-info/zip-safe
crystal_builder_step-2022.7.31.dist-info/RECORD
