Metadata-Version: 2.1
Name: crystal-builder-step
Version: 2022.7.31
Summary: A SEAMM plug-in for creating crystals from prototypes, including Strukturbericht designations.
Home-page: https://github.com/molssi-seamm/crystal_builder_step
Author: Paul Saxe
Author-email: psaxe@molssi.org
License: BSD-3-Clause
Keywords: SEAMM,plug-in,flowchart,crystal,Strukturbericht,prototype
Platform: Linux
Platform: Mac OS-X
Platform: Unix
Platform: Windows
Classifier: Development Status :: 5 - Production/Stable
Classifier: Intended Audience :: Science/Research
Classifier: Topic :: Scientific/Engineering :: Chemistry
Classifier: Topic :: Scientific/Engineering :: Physics
Classifier: License :: OSI Approved :: BSD License
Classifier: Natural Language :: English
Classifier: Programming Language :: Python :: 3 :: Only
Classifier: Programming Language :: Python :: 3.8
Classifier: Programming Language :: Python :: 3.9
License-File: LICENSE
License-File: AUTHORS.rst
Requires-Dist: openpyxl
Requires-Dist: pycifrw
Requires-Dist: seamm
Requires-Dist: seamm-util
Requires-Dist: seamm-widgets
